GamePlusEditor/CodeEditorPython.py
GamePlusEditor/CodeEditorUrsaVisor.py
GamePlusEditor/ColorMenu.py
GamePlusEditor/ConfigEditor.py
GamePlusEditor/ConfigProjectMenu.py
GamePlusEditor/CurrentFolderNameReturner.py
GamePlusEditor/DirectionBox.py
GamePlusEditor/Gizmo.py
GamePlusEditor/Main.py
GamePlusEditor/OpenFile.py
GamePlusEditor/OtherStuff.py
GamePlusEditor/PositionGizmo.py
GamePlusEditor/ProjectEditor.py
GamePlusEditor/ProjectExporter.py
GamePlusEditor/ProjectLoader.py
GamePlusEditor/ProjectReader.py
GamePlusEditor/ProjectSaver.py
GamePlusEditor/ProjectSavingEncoder.py
GamePlusEditor/RecentProjectFinder.py
GamePlusEditor/SceneEditor.py
GamePlusEditor/StartingUI.py
GamePlusEditor/SyntaxHighlighter.py
GamePlusEditor/__init__.py
GamePlusEditor/launcher.py
GamePlusEditor/CoreFiles/BlueLink.py
GamePlusEditor/CoreFiles/ConfigProjectMenu.py
GamePlusEditor/CoreFiles/InstructionList.py
GamePlusEditor/CoreFiles/InstructionMenu.py
GamePlusEditor/CoreFiles/NewCursor.py
GamePlusEditor/CoreFiles/Terminal.py
GamePlusEditor/CoreFiles/TrueFalseIndicator.py
GamePlusEditor/CoreFiles/__init__.py
GamePlusEditor/FileSystem/FileMenu.py
GamePlusEditor/GizmoStuff/BaseGizmo.py
GamePlusEditor/GizmoStuff/GizmoManager.py
GamePlusEditor/GizmoStuff/GizmoUpdater.py
GamePlusEditor/GizmoStuff/PositionGizmo.py
GamePlusEditor/GizmoStuff/RotationGizmo.py
GamePlusEditor/GizmoStuff/ScaleGizmo.py
GamePlusEditor/GizmoStuff/__init__.py
GamePlusEditor/Images/AddFile.png
GamePlusEditor/Images/AddFolder.png
GamePlusEditor/Images/AddFolder2.png
GamePlusEditor/Images/BlueLinkMouse.png
GamePlusEditor/Images/File.png
GamePlusEditor/Images/Folder.png
GamePlusEditor/Images/Plug-in icon removed bg.png
GamePlusEditor/Images/Plug-in icon.png
GamePlusEditor/Images/PosSnappingIcon bad.jpg
GamePlusEditor/Images/PosSnappingIcon-BgRemoved.png
GamePlusEditor/Images/Search.png
GamePlusEditor/Models/PositionGizmo.mtl
GamePlusEditor/Models/PositionGizmo.obj
GamePlusEditor/Models/RotationGizmo.blend
GamePlusEditor-0.0.9.dist-info/LICENSE
GamePlusEditor-0.0.9.dist-info/METADATA
GamePlusEditor-0.0.9.dist-info/WHEEL
GamePlusEditor-0.0.9.dist-info/top_level.txt
GamePlusEditor-0.0.9.dist-info/RECORD
