Metadata-Version: 2.1
Name: GamePlusEditor
Version: 0.0.9
Summary: A gui game maker written in python
Home-page: https://github.com/IndividualCoder/GamePlus-Editor
Author: Prince
Author-email: IndividualCoder@gmail.com
License: MIT
Keywords: game development
Requires-Python: >=3.10
License-File: LICENSE
Requires-Dist: panda3d
Requires-Dist: panda3d-gltf
Requires-Dist: pillow
Requires-Dist: pyperclip
Requires-Dist: screeninfo
Requires-Dist: psutil
Requires-Dist: ursina
